resources/__init__.py
resources/charts/__init__.py
resources/charts/bitcoincore/.helmignore
resources/charts/bitcoincore/Chart.yaml
resources/charts/bitcoincore/values.yaml
resources/charts/bitcoincore/charts/cln/.helmignore
resources/charts/bitcoincore/charts/cln/Chart.yaml
resources/charts/bitcoincore/charts/cln/values.yaml
resources/charts/bitcoincore/charts/cln/templates/_helpers.tpl
resources/charts/bitcoincore/charts/cln/templates/configmap.yaml
resources/charts/bitcoincore/charts/cln/templates/pod.yaml
resources/charts/bitcoincore/charts/cln/templates/service.yaml
resources/charts/bitcoincore/charts/cln/templates/servicemonitor.yaml
resources/charts/bitcoincore/charts/lnd/Chart.yaml
resources/charts/bitcoincore/charts/lnd/values.yaml
resources/charts/bitcoincore/charts/lnd/templates/_helpers.tpl
resources/charts/bitcoincore/charts/lnd/templates/configmap.yaml
resources/charts/bitcoincore/charts/lnd/templates/pod.yaml
resources/charts/bitcoincore/charts/lnd/templates/service.yaml
resources/charts/bitcoincore/charts/lnd/templates/servicemonitor.yaml
resources/charts/bitcoincore/templates/NOTES.txt
resources/charts/bitcoincore/templates/_helpers.tpl
resources/charts/bitcoincore/templates/configmap.yaml
resources/charts/bitcoincore/templates/pod.yaml
resources/charts/bitcoincore/templates/service.yaml
resources/charts/bitcoincore/templates/servicemonitor.yaml
resources/charts/caddy/.helmignore
resources/charts/caddy/Chart.yaml
resources/charts/caddy/values.yaml
resources/charts/caddy/templates/NOTES.txt
resources/charts/caddy/templates/_helpers.tpl
resources/charts/caddy/templates/configmap.yaml
resources/charts/caddy/templates/ingress.yaml
resources/charts/caddy/templates/pod.yaml
resources/charts/caddy/templates/service.yaml
resources/charts/commander/.helmignore
resources/charts/commander/Chart.yaml
resources/charts/commander/values.yaml
resources/charts/commander/templates/NOTES.txt
resources/charts/commander/templates/_helpers.tpl
warnet-1.1.17.dist-info/licenses/LICENSE
warnet-1.1.17.dist-info/METADATA
warnet-1.1.17.dist-info/WHEEL
warnet-1.1.17.dist-info/entry_points.txt
warnet-1.1.17.dist-info/top_level.txt
warnet-1.1.17.dist-info/RECORD
