Metadata-Version: 2.4
Name: warnet
Version: 1.1.17
Summary: Monitor and analyze the emergent behaviours of bitcoin networks
License: MIT
Project-URL: Homepage, https://warnet.dev
Project-URL: GitHub, https://github.com/bitcoin-dev-project/warnet
Project-URL: Pypi, https://pypi.org/project/warnet/
Keywords: bitcoin,warnet
Classifier: Development Status :: 4 - Beta
Classifier: Intended Audience :: Developers
Classifier: License :: OSI Approved :: MIT License
Classifier: Programming Language :: Python :: 3.9
Classifier: Programming Language :: Python :: 3.10
Classifier: Programming Language :: Python :: 3.11
Classifier: Programming Language :: Python :: 3.12
Requires-Python: >=3.9
License-File: LICENSE
Requires-Dist: click==8.1.7
Requires-Dist: docker==7.1.0
Requires-Dist: flask==3.0.3
Requires-Dist: inquirer==3.4.0
Requires-Dist: kubernetes==30.1.0
Requires-Dist: rich==13.7.1
Requires-Dist: tabulate==0.9.0
Requires-Dist: PyYAML==6.0.2
Requires-Dist: pexpect==4.9.0
Provides-Extra: build
Requires-Dist: twine; extra == "build"
Requires-Dist: build; extra == "build"
Dynamic: license-file
